achievements.py
achievements-0.2.dist-info/LICENSE
achievements-0.2.dist-info/METADATA
achievements-0.2.dist-info/WHEEL
achievements-0.2.dist-info/top_level.txt
achievements-0.2.dist-info/RECORD
